README.md
setup.py
configurations/__init__.py
configurations/config.py
run/__init__.py
run/run.py
utilities/__init__.py
utilities/user_input_file.py
weather_api/WeatherAPI.py
weather_api/__init__.py
weatherapplication_arorarajat084.egg-info/PKG-INFO
weatherapplication_arorarajat084.egg-info/SOURCES.txt
weatherapplication_arorarajat084.egg-info/dependency_links.txt
weatherapplication_arorarajat084.egg-info/top_level.txt