Metadata-Version: 2.1
Name: weatherapplication-arorarajat084
Version: 0.0.2
Summary: A Python project build on top of Weather API.
Home-page: https://github.com/pypa/sampleproject
Author: Rajat Arora
Author-email: arora.rajat084@gmail.com
License: UNKNOWN
Platform: UNKNOWN
Classifier: Programming Language :: Python :: 3
Classifier: License :: OSI Approved :: MIT License
Classifier: Operating System :: OS Independent
Requires-Python: >=3.6
